{"id": "tt0089941", "cast": [{"character": "Oscar 'Manny' Manheim", "name": "Jon Voight"}, {"character": "Buck", "name": "Eric Roberts"}, {"character": "Sara", "name": "Rebecca De Mornay"}, {"character": "Frank Barstow", "name": "Kyle T. Heffner"}, {"character": "Ranken", "name": "John P. Ryan"}, {"character": "Dave Prince", "name": "T. K. Carter"}, {"character": "Eddie MacDonald", "name": "Kenneth McMillan"}, {"character": "Ruby", "name": "Stacey Pickren"}, {"character": "Conlan", "name": "Walter Wyatt"}, {"character": "Jonah", "name": "Edward Bunker"}, {"character": "Al Turner", "name": "Reid Cruickshanks"}, {"character": "Fat Con", "name": "Dan Wray"}, {"character": "Short Con", "name": "Michael Lee Gogin"}, {"character": "Tall Con", "name": "John Bloom"}, {"character": "Old Con", "name": "Hank Worden"}, {"character": "Boxer", "name": "Danny Trejo"}, {"character": "Guard", "name": "Tom Lister Jr."}, {"character": "Cop (uncredited)", "name": "Dennis Franz"}, {"character": "Cat Con", "name": "John Otrin"}, {"character": "Queen Con", "name": "Norman Alexander Gibbs"}], "crew": [{"job": "Director", "name": "Andrei Konchalovsky"}, {"job": "Screenplay", "name": "Edward Bunker"}, {"job": "Original Music Composer", "name": "Trevor Jones"}, {"job": "Screenplay", "name": "\u0110or\u0111e Mili\u0107evi\u0107"}, {"job": "Screenplay", "name": "Paul Zindel"}, {"job": "Producer", "name": "Yoram Globus"}, {"job": "Producer", "name": "Menahem Golan"}, {"job": "Screenplay", "name": "Akira Kurosawa"}], "title": "Runaway Train", "genres": ["Action", "Thriller"], "keywords": ["attempt to escape", "alaska", "train", "prison escape"], "original_language": "English", "rating": "R", "release_date": "1985-11-15", "revenue": 7936012.0, "runtime": 111, "summary": "A hardened convict and a younger prisoner escape from a brutal prison in the middle of winter only to find themselves on an out-of-control train with a female railway worker while being pursued by the vengeful head of security.", "tmdb_score_value": 7.0, "tmdb_score_count": 166, "imdb_score_value": 7.3, "imdb_score_count": 22980, "meta_score_value": 0.0, "meta_score_count": 0}