{"id": "tt0116999", "cast": [{"character": "Bessie", "name": "Diane Keaton"}, {"character": "Lee", "name": "Meryl Streep"}, {"character": "Hank", "name": "Leonardo DiCaprio"}, {"character": "Marvin", "name": "Robert De Niro"}, {"character": "Marvin", "name": "Hume Cronyn"}, {"character": "Ruth", "name": "Gwen Verdon"}, {"character": "Charlie", "name": "Hal Scardino"}, {"character": "Bob", "name": "Dan Hedaya"}, {"character": "Dr. Charlotte", "name": "Margo Martindale"}, {"character": "Retirement Home Director", "name": "Cynthia Nixon"}, {"character": "Coral", "name": "Kelly Ripa"}, {"character": "Lance", "name": "John Callahan"}, {"character": "Bruno", "name": "Joe Lisi"}, {"character": "Janine", "name": "Bitty Schram"}, {"character": "Novice", "name": "Lizbeth MacKay"}, {"character": "Beauty Shop Lady", "name": "Olga Merediz"}, {"character": "Gas Station Guy", "name": "Steve DuMouchel"}, {"character": "Nun on Phone", "name": "Helen Stenborg"}], "crew": [{"job": "Director", "name": "Jerry Zaks"}, {"job": "Screenplay", "name": "Scott McPherson"}, {"job": "Original Music Composer", "name": "Rachel Portman"}, {"job": "Producer", "name": "Robert De Niro"}, {"job": "Producer", "name": "Jane Rosenthal"}, {"job": "Producer", "name": "Scott Rudin"}], "title": "Marvin's Room", "genres": ["Drama"], "keywords": ["sibling relationship", "sister", "leukemia", "reunion", "cancer", "bone marrow transplant"], "original_language": "English", "rating": "PG-13", "release_date": "1996-12-18", "revenue": 12803305.0, "runtime": 98, "summary": "Estranged since their father's first stroke some 17 years earlier, Lee and Bessie lead separate lives in separate states. Lee's son, Hank, finds himself committed to a mental institution after setting fire to his mother's house. His younger brother, Charlie, seems unfazed by his brother's eccentricities or his mother's seeming disinterest. When Lee comes to the asylum to spring Hank for a week in Florida so that he can be tested as a possible bone marrow donor for Bessie, Hank is incredulous. \"I didn't even know you had a sister,\" he says. \"Remember, every Christmas, when I used to say 'Well, looks like Aunt Bessie didn't send us a card again this year?'\" \"Oh yeah,\" Hank says. Meanwhile, Marvin, the two women's bedridden father, has \"been dying for the past twenty years.\" \"He's doing it real slow so I don't miss anything,\" Bessie tells Dr. Wally. In Bessie's regular doctor's absence, it has fallen to Dr. Wally to inform Bessie that she has leukemia and will die without a bone marrow ...", "tokens": ["estrang", "sinc", "father", "first", "stroke", "17", "year", "earlier", "lee", "bessi", "lead", "separ", "live", "separ", "state", "lee", "son", "hank", "find", "commit", "mental", "institut", "set", "fire", "mother", "hous", "hi", "younger", "brother", "charli", "seem", "unfaz", "brother", "eccentr", "mother", "seem", "disinterest", "when", "lee", "come", "asylum", "spring", "hank", "week", "florida", "test", "possibl", "bone", "marrow", "donor", "bessi", "hank", "incredul", "i", "even", "know", "sister", "sai", "rememb", "everi", "christma", "i", "us", "sai", "well", "look", "like", "aunt", "bessi", "send", "us", "card", "year", "oh", "yeah", "hank", "sai", "meanwhil", "marvin", "two", "women", "bedridden", "father", "dy", "past", "twenti", "year", "he", "real", "slow", "i", "miss", "anyth", "bessi", "tell", "dr", "walli", "in", "bessi", "regular", "doctor", "absenc", "fallen", "dr", "walli", "inform", "bessi", "leukemia", "die", "without", "bone", "marrow"], "tmdb_score_value": 6.7, "tmdb_score_count": 185, "imdb_score_value": 6.7, "imdb_score_count": 22318, "meta_score_value": 68.0, "meta_score_count": 20}