{"id": "tt0110475", "cast": [{"character": "Stanley Ipkiss / The Mask", "name": "Jim Carrey"}, {"character": "Tina Carlyle", "name": "Cameron Diaz"}, {"character": "Mrs. Peenman", "name": "Nancy Fish"}, {"character": "Irv", "name": "Tim Bagley"}, {"character": "Burt", "name": "Johnny Williams"}, {"character": "Lieutenant Mitch Kellaway", "name": "Peter Riegert"}, {"character": "Dorian Tyrrell", "name": "Peter Greene"}, {"character": "Peggy Brandt", "name": "Amy Yasbeck"}, {"character": "Charlie Schumaker", "name": "Richard Jeni"}, {"character": "Niko", "name": "Orestes Matacena"}, {"character": "Dancer", "name": "Anne Fletcher"}, {"character": "Freeze", "name": "Reg E. Cathey"}, {"character": "Doyle", "name": "Jim Doughan"}, {"character": "Sweet Eddy", "name": "Denis Forest"}, {"character": "Bobby the Bouncer", "name": "Jeremy Roberts"}, {"character": "Dr. Arthur Neuman", "name": "Ben Stein"}], "crew": [{"job": "Director", "name": "Chuck Russell"}, {"job": "Screenplay", "name": "Mike Werb"}, {"job": "Original Music Composer", "name": "Randy Edelman"}], "title": "The Mask", "genres": ["Romance", "Comedy", "Crime", "Fantasy"], "keywords": ["dual identity", "bank", "mockery", "green", "balloon", "jail cell", "norse mythology"], "original_language": "English", "rating": "PG-13", "release_date": "1994-07-29", "revenue": 351583400.0, "runtime": 101, "summary": "Stanley Ipkiss is a bank clerk that is an incredibly nice man. Unfortunately, he is too nice for his own good and is a pushover when it comes to confrontations. After one of the worst days of his life, he finds a mask that depicts Loki, the Norse night god of mischief. Now, when he puts it on, he becomes his inner, self: a cartoon romantic wild man. However, a small time crime boss, Dorian Tyrel , comes across this character dubbed \"The Mask\" by the media. After Ipkiss's alter ego indirectly kills his friend in crime, Tyrel now wants this green-faced goon destroyed.", "tokens": ["stanlei", "ipkiss", "jim", "carrei", "clerk", "edg", "citi", "bank", "shy", "luckless", "romant", "regularli", "bulli", "nearli", "everyon", "around", "includ", "boss", "eamonn", "roch", "landladi", "mr", "peeman", "nanci", "fish", "car", "mechan", "hi", "friend", "fox", "terrier", "milo", "co", "worker", "charli", "richard", "jeni", "meanwhil", "gangster", "dorian", "tyrel", "peter", "green", "run", "exclus", "coco", "bongo", "nightclub", "plot", "overthrow", "boss", "niko", "orest", "matacena", "tyrel", "send", "singer", "girlfriend", "tina", "carlyl", "cameron", "diaz", "stanlei", "bank", "hidden", "camera", "prepar", "rob", "bank", "stanlei", "smitten", "tina", "seem", "reciproc", "later", "night", "deni", "entranc", "coco", "bongo", "strand", "broken", "rental", "car", "citi", "filthi", "harbor", "find", "mysteri", "wooden", "mask", "next", "pile", "garbag", "first", "mistak", "drown", "man", "he", "take", "object", "home", "jokingli", "put", "the", "mask", "wrap", "around", "head", "transform", "wackili", "suit", "green", "head", "figur", "the", "mask", "trickster", "realiti", "bend", "power", "physic", "impervi", "without", "person", "inhibit", "exact", "comic", "reveng", "stanlei", "tormentor", "scare", "street", "gang", "attempt", "mug", "the", "next", "morn", "stanlei", "encount", "world", "weari", "edg", "citi", "detect", "lieuten", "kellawai", "peter", "riegert", "newspap", "report", "peggi", "brandt", "ami", "yasbeck", "investig", "mask", "activ", "previou", "night", "despit", "threat", "temptat", "us", "mask", "overwhelm", "put", "back", "even", "need", "monei", "attend", "tina", "perform", "coco", "bongo", "mask", "noisili", "interrupt", "tyrel", "bank", "robberi", "steal", "target", "monei", "tyrel", "henchman", "freez", "reg", "e", "cathei", "shot", "polic", "respond", "disturb", "the", "mask", "bui", "entri", "coco", "bongo", "rock", "joint", "danc", "exuberantli", "tina", "front", "cheer", "crowd", "tyrel", "call", "awai", "sweet", "eddi", "deni", "forest", "after", "freez", "di", "tyrel", "arm", "tyrel", "violent", "ask", "respons", "eddi", "point", "mask", "danc", "tina", "at", "end", "danc", "mask", "give", "tina", "kiss", "liter", "blow", "shoe", "confront", "tyrel", "pull", "gun", "shoot", "part", "mask", "tie", "transform", "back", "stanlei", "distinct", "pajama", "the", "mask", "escap", "tyrel", "temporarili", "arrest", "bank", "robberi", "lt", "kellawai", "also", "find", "pajama", "scrap", "also", "inform", "policeman", "found", "freez", "dead", "bodi", "kellawai", "confront", "stanlei", "apart", "weari", "stanlei", "discov", "bank", "monei", "stuf", "closet", "stanlei", "later", "consult", "expert", "mask", "name", "arthur", "neumann", "ben", "stein", "tell", "object", "depict", "loki", "nors", "god", "dark", "mischief", "despit", "tyrel", "lt", "kellawai", "hunt", "confid", "stanlei", "stand", "boss", "arrang", "tina", "meet", "mask", "local", "landfil", "park", "the", "meet", "goe", "badli", "mask", "advanc", "scare", "tina", "awai", "lt", "kellawai", "arriv", "attempt", "arrest", "the", "mask", "toi", "enrag", "offic", "zoom", "park", "trick", "larg", "group", "edg", "citi", "polic", "offic", "join", "mass", "perform", "product", "song", "cuban", "pete", "stanlei", "manag", "get", "mask", "peggi", "help", "escap", "betrai", "tyrel", "$50", "000", "mob", "bounti", "tyrel", "tri", "mask", "becom", "demon", "monster", "demand", "know", "stanlei", "monei", "took", "stanlei", "shown", "on", "mob", "car", "tyrel", "henchmen", "search", "stanlei", "apart", "reclaim", "monei", "stanlei", "later", "liter", "dump", "kellawai", "lap", "green", "rubber", "mask", "thrown", "jail", "tina", "sympathet", "visit", "stanlei", "cell", "urg", "flee", "citi", "she", "attempt", "pursu", "orlando", "nil", "allen", "stewart", "corner", "tyrel", "upon", "told", "orlando", "attempt", "leav", "citi", "tina", "forcefulli", "taken", "raid", "chariti", "ball", "coco", "bongo", "host", "niko", "attend", "citi", "elit", "includ", "citi", "mayor", "mitchel", "tilton", "ivori", "ocean", "upon", "arriv", "mask", "tyrel", "kill", "niko", "gunfight", "prepar", "destroi", "club", "tina", "meanwhil", "milo", "help", "stanlei", "break", "cell", "go", "club", "stop", "tyrel", "eventu", "drag", "lt", "kellawai", "along", "upon", "arriv", "stanlei", "tell", "lt", "kellawai", "call", "backup", "sneak", "coco", "bongo", "gun", "after", "brief", "initi", "success", "assist", "charli", "stanlei", "spot", "orlando", "captur", "stanlei", "anyth", "tina", "trick", "tyrel", "take", "mask", "recov", "milo", "turn", "dog", "cartoonish", "pitbul", "defeat", "tyrel", "men", "stanlei", "fight", "dorian", "stanlei", "recov", "mask", "wear", "on", "last", "time", "us", "abil", "save", "tina", "swallow", "tyrel", "bomb", "flush", "tyrel", "drain", "club", "ornament", "fountain", "lead", "death", "the", "polic", "arriv", "arrest", "tyrel", "remain", "henchmen", "mayor", "mitchel", "tilton", "wit", "deduc", "tyrel", "mask", "start", "order", "lt", "kellawai", "releas", "stanlei", "after", "stanlei", "tina", "charli", "milo", "leav", "mayor", "mitchel", "tilton", "tell", "lt", "kellawai", "would", "like", "word", "as", "sun", "rise", "stanlei", "tina", "milo", "charli", "take", "mask", "back", "harbor", "tina", "stanlei", "throw", "back", "water", "share", "first", "kiss", "charli", "attempt", "retriev", "mask", "find", "milo", "swim", "awai"], "tmdb_score_value": 6.7, "tmdb_score_count": 3415, "imdb_score_value": 6.9, "imdb_score_count": 295449, "meta_score_value": 56.0, "meta_score_count": 12}