{"id": "tt0242423", "cast": [{"character": "Jesse", "name": "Ashton Kutcher"}, {"character": "Chester", "name": "Seann William Scott"}, {"character": "Christie Boner", "name": "Kristy Swanson"}, {"character": "Wanda", "name": "Jennifer Garner"}, {"character": "Wilma", "name": "Marla Sokoloff"}, {"character": "Nelson", "name": "David Herman"}, {"character": "Zoltan", "name": "Hal Sparks"}, {"character": "Tommy", "name": "Charlie O'Connell"}, {"character": "Mr. Pizzacoli", "name": "John Toles-Bey"}, {"character": "Alien Nordic Dude #1", "name": "Christian Middelthon"}, {"character": "Alien Nordic Dude #2", "name": "Dave Bannick"}, {"character": "Jeff", "name": "Turtle"}, {"character": "Zarnoff", "name": "Bob Clendenin"}, {"character": "Zelmina", "name": "Mary Lynn Rajskub"}, {"character": "Zellner", "name": "Kevin Christy"}], "crew": [{"job": "Director", "name": "Danny Leiner"}, {"job": "Screenplay", "name": "Philip Stark"}, {"job": "Original Music Composer", "name": "David Kitay"}, {"job": "Producer", "name": "Broderick Johnson"}, {"job": "Producer", "name": "Andrew A. Kosove"}, {"job": "Producer", "name": "Gil Netter"}, {"job": "Producer", "name": "Wayne Allan Rice"}], "title": "Dude, Where's My Car?", "genres": ["Comedy"], "keywords": ["dude", "amnesia", "idiot", "friendship", "cannabis", "hangover", "spoof", "teenager", "drugs", "alcohol abuse", "celebration", "car", "duringcreditsstinger", "child"], "original_language": "English", "rating": "PG-13", "release_date": "2000-12-15", "revenue": 73180720.0, "runtime": 83, "summary": "Roommates Jesse and Chester, both who have more than just a few cards short of a full deck, are stoner dudes who don't even do their jobs as pizza delivery guys well. They awaken one morning having little recollection of what they did the previous night, due to being wasted. They discover that their kitchen is full of prepackaged pudding, how they got all the pudding they are unaware. From a telephone message they receive, they come to the realization that at some point during the previous night they were at a party at the house of their girlfriends, twins Wanda and Wilma, and that today is their one year anniversary, which they did remember as they already bought the twins gifts. But the worst thing in not remembering what happened last night is that Jesse's car is missing. In trying to find out what happened to the car, they believe they have to recreate the feeling and mindset of last night, meaning getting wasted all over again. In trying to find the car, they, being the types ...", "tmdb_score_value": 5.3, "tmdb_score_count": 674, "imdb_score_value": 5.5, "imdb_score_count": 124263, "meta_score_value": 30.0, "meta_score_count": 17}