{"id": "tt0338001", "cast": [{"character": "Emile", "name": "Ian McKellen"}, {"character": "Nadia", "name": "Deborah Unger"}, {"character": "Freddy", "name": "Tygh Runyan"}, {"character": "Carl", "name": "Chris William Martin"}, {"character": "Tom", "name": "Ian Tracey"}, {"character": "Alice", "name": "Janet Wright"}], "crew": [{"job": "Director", "name": "Carl Bessai"}], "title": "\u00c9mile", "genres": ["Drama"], "keywords": ["independent film"], "original_language": "English", "rating": "R", "release_date": "2003-01-01", "revenue": 0.0, "runtime": 92, "summary": "As a young man, Emile left his Saskatchewan farm life behind to head to university in Britain, with his brothers, the older brusque and controlling Carl and the younger sensitive Freddy, left to run the family farm. This move was despite Freddy showing greater potential and thus probably benefiting more from academic life. However, Carl wouldn't allow Freddy to leave because of his mechanical expertise which was required to tend to the farm equipment. Emile vowed to return, but never did, which affected Freddy the most. Now in early retirement, Emile, still living in Britain, travels to Victoria, Canada to accept an honorary degree from the university there. In Victoria, he decides to stay with now deceased Carl's grown daughter Nadia, and Nadia's ten year old daughter Maria. Emile had never made any attempt over the years to connect with Nadia or Maria, who only really know him by name. On the surface to Nadia, Emile's visit is purely a need on his part for a free bed while in ...", "tokens": ["as", "young", "man", "emil", "left", "saskatchewan", "farm", "life", "behind", "head", "univers", "britain", "brother", "older", "brusqu", "control", "carl", "younger", "sensit", "freddi", "left", "run", "famili", "farm", "thi", "move", "despit", "freddi", "show", "greater", "potenti", "thu", "probabl", "benefit", "academ", "life", "howev", "carl", "allow", "freddi", "leav", "mechan", "expertis", "requir", "tend", "farm", "equip", "emil", "vow", "return", "never", "affect", "freddi", "now", "earli", "retir", "emil", "still", "live", "britain", "travel", "victoria", "canada", "accept", "honorari", "degre", "univers", "in", "victoria", "decid", "stai", "deceas", "carl", "grown", "daughter", "nadia", "nadia", "ten", "year", "old", "daughter", "maria", "emil", "never", "made", "attempt", "year", "connect", "nadia", "maria", "realli", "know", "name", "on", "surfac", "nadia", "emil", "visit", "pure", "need", "part", "free", "bed"], "tmdb_score_value": 6.0, "tmdb_score_count": 4, "imdb_score_value": 6.4, "imdb_score_count": 672, "meta_score_value": 58.0, "meta_score_count": 10}