{"id": "tt0441000", "cast": [{"character": "Himself", "name": "Wild Man Fischer"}], "crew": [{"job": "Director", "name": "Josh Rubin"}], "title": "Derailroaded", "genres": ["Documentary", "Music"], "keywords": [], "original_language": "English", "rating": "NOT RATED", "release_date": "2005-03-01", "revenue": 0.0, "runtime": 86, "summary": "A documentary on the life and music of manic-depressive, paranoid-schizophrenic cult music icon Wild Man Fischer.", "tokens": ["a", "documentari", "life", "music", "manic", "depress", "paranoid", "schizophren", "cult", "music", "icon", "wild", "man", "fischer"], "tmdb_score_value": 9.0, "tmdb_score_count": 2, "imdb_score_value": 7.4, "imdb_score_count": 189, "meta_score_value": 57.0, "meta_score_count": 7}