{"id": "tt0482572", "cast": [{"character": "Ray Tierney", "name": "Edward Norton"}, {"character": "Francis Tierney, Sr.", "name": "Jon Voight"}, {"character": "Jimmy Eagan", "name": "Colin Farrell"}, {"character": "Francis Tierney, Jr.", "name": "Noah Emmerich"}, {"character": "Abby Tierney", "name": "Jennifer Ehle"}, {"character": "Ruben Santiago", "name": "John Ortiz"}, {"character": "Eddie Carbone", "name": "Frank Grillo"}, {"character": "Kenny Dugan", "name": "Shea Whigham"}, {"character": "Megan Egan", "name": "Lake Bell"}, {"character": "Tasha", "name": "Carmen Ejogo"}, {"character": "Coco Dominguez", "name": "Manny P\u00e9rez"}, {"character": "Bill Avery", "name": "Wayne Duvall"}, {"character": "Angel Tezo", "name": "Ram\u00f3n Rodr\u00edguez"}, {"character": "Eladio Casado", "name": "Rick Gonzalez"}, {"character": "Carlos Bragon", "name": "Maximiliano Hern\u00e1ndez"}, {"character": "Maureen Tierney", "name": "Leslie Denniston"}, {"character": "Caitlin Tierney", "name": "Hannah Riggins"}, {"character": "Matthew Egan", "name": "Ty Simpkins"}, {"character": "Shannon Egan", "name": "Ryan Simpkins"}], "crew": [{"job": "Director", "name": "Gavin O'Connor"}, {"job": "Screenplay", "name": "Joe Carnahan"}, {"job": "Screenplay", "name": "Gavin O'Connor"}, {"job": "Producer", "name": "Greg O'Connor"}, {"job": "Producer", "name": "Josh Fagin"}, {"job": "Producer", "name": "Robert Hopes"}, {"job": "Original Music Composer", "name": "Mark Isham"}], "title": "Pride and Glory", "genres": ["Thriller", "Crime", "Drama"], "keywords": ["megacity", "brother-in-law", "police"], "original_language": "English", "rating": "R", "release_date": "2008-09-09", "revenue": 31148328.0, "runtime": 130, "summary": "A family of police officers - patriarch, two sons, and a son-in-law - deals with corruption in a precinct in Washington Heights. Four officers die in an ambush at a drug dealer's apartment. It's brother Francis's precinct, so when the investigation led by brother Ray finds hints of police corruption, there's pressure to close ranks and save Frankie's career. Dad, a police brass, promises Ray that he and Frankie can clean things up, and Ray should focus on catching the drug dealer who killed the cops. Meanwhile, brother-in-law Jimmy, a hothead and an enforcer, is visited at home by a lowlife. Is Jimmy involved in the corruption? Where can this take the family?", "tokens": ["open", "footbal", "game", "nypd", "plai", "jimmi", "egan", "colin", "farrel", "main", "player", "get", "word", "coach", "everyth", "keep", "lead", "14", "10", "he", "tell", "team", "believ", "rai", "tiernei", "edward", "norton", "sit", "megan", "egan", "lake", "bell", "watch", "game", "franci", "tiernei", "jr", "noah", "emmerich", "brother", "thei", "win", "cheer", "around", "franci", "jr", "get", "call", "bunch", "men", "divis", "franci", "co", "got", "kill", "four", "offic", "franci", "jr", "rai", "run", "scene", "shabbi", "apart", "bodi", "everywher", "by", "door", "window", "everyth", "mess", "an", "offic", "taken", "apart", "stretcher", "jimmi", "run", "footbal", "game", "look", "dead", "cop", "start", "get", "angri", "lock", "bathroom", "cry", "break", "mirror", "he", "upset", "franci", "sr", "jon", "voight", "scene", "well", "bigshot", "depart", "although", "100%", "clear", "role", "make", "order", "around", "in", "hospit", "rai", "jimmi", "sit", "offic", "taken", "di", "you", "hear", "wail", "wife", "it", "friend", "everyon", "appear", "rai", "goe", "bathroom", "start", "pop", "prescript", "pill", "franci", "sr", "father", "come", "look", "son", "tell", "appli", "task", "forc", "investig", "murder", "men", "rai", "mention", "readi", "father", "disagre", "sai", "dead", "man", "would", "done", "rai", "tri", "demur", "cite", "old", "incid", "make", "go", "miss", "person", "divis", "father", "none", "end", "strongarm", "join", "task", "forc", "cut", "allei", "everyth", "happen", "rai", "fellow", "task", "forc", "offic", "look", "window", "know", "whoever", "shooter", "got", "shot", "ran", "thei", "follow", "blood", "stop", "gui", "must", "gotten", "car", "know", "anyth", "thei", "find", "cell", "phone", "snow", "thei", "gotten", "handout", "six", "prime", "suspect", "an", "offic", "come", "ask", "anyon", "speak", "spanish", "kid", "might", "seen", "someth", "rai", "sai", "speak", "go", "small", "conveni", "store", "man", "yell", "thing", "spanish", "note", "spanish", "subtitl", "movi", "rai", "tell", "calm", "get", "face", "get", "wife", "take", "kid", "the", "kid", "sleep", "couch", "woken", "rai", "come", "rai", "ask", "question", "find", "kid", "shooter", "bleed", "stomach", "look", "scare", "shown", "pictur", "find", "name", "angel", "tezo", "ramon", "rodriguez", "when", "rai", "ask", "color", "car", "told", "white", "four", "door", "car", "cab", "car", "yellow", "on", "cut", "car", "abandon", "green", "non", "industri", "area", "jimmi", "kenni", "shea", "whigham", "sandi", "john", "ortiz", "eddi", "frank", "grillo", "check", "car", "appar", "deal", "gone", "bad", "thei", "try", "kill", "tezo", "get", "monei", "everyth", "went", "bad", "tezo", "got", "awai", "kill", "peopl", "took", "monei", "and", "kill", "driver", "thei", "set", "find", "kill", "tezo", "finger", "know", "kill", "thei", "talk", "drug", "payoff", "monei", "hit", "obvious", "dirti", "cop", "first", "torch", "car", "everyth", "insid", "cut", "tezo", "get", "doctor", "sew", "gut", "wound", "safehous", "croni", "count", "monei", "tezo", "obvious", "temper", "yell", "doctor", "lot", "when", "doctor", "done", "hand", "monei", "tezo", "girl", "hand", "tezo", "potato", "tezo", "put", "gun", "kiss", "shoot", "doctor", "us", "potato", "silenc", "rai", "sit", "houseboat", "look", "crime", "scene", "photo", "see", "someth", "strang", "photo", "on", "men", "kill", "bootlac", "belt", "he", "make", "call", "come", "much", "it", "christma", "next", "dai", "rai", "goe", "townhous", "put", "hand", "knock", "drop", "small", "gift", "porch", "instead", "as", "leav", "door", "open", "rai", "wife", "thei", "obvious", "estrang", "reveal", "on", "month", "awai", "divorc", "thei", "appar", "lot", "difficulti", "care", "go", "anymor", "part", "sadli", "eddi", "sandi", "go", "conveni", "store", "get", "everyon", "pistol", "whip", "cashier", "tell", "inform", "admit", "know", "tezo", "the", "man", "given", "24", "hour", "get", "inform", "kill", "eddi", "show", "unstabl", "put", "gun", "man", "head", "fire", "empti", "thei", "pop", "regist", "take", "monei", "well", "franci", "jr", "wife", "abbi", "jennif", "ehl", "sit", "bed", "bald", "head", "look", "sick", "she", "take", "pill", "franci", "come", "ask", "want", "parti", "she", "sai", "miss", "anyth", "downstair", "lot", "cook", "go", "franci", "sr", "drunk", "kid", "run", "around", "want", "open", "present", "upstair", "franci", "jr", "give", "abbi", "ring", "sai", "love", "forev", "abbi", "almost", "start", "cry", "thei", "go", "downstair", "jimmi", "wife", "famili", "come", "everyon", "begin", "open", "present", "at", "dinner", "tabl", "franci", "sr", "drunk", "start", "overprais", "rai", "sai", "alwai", "brain", "would", "soon", "investig", "daughter", "megan", "huge", "heart", "becam", "nurs", "he", "sai", "much", "franci", "jr", "jimmi", "son", "law", "it", "becom", "strang", "awkward", "tabl", "goe", "pretti", "quiet", "franci", "jimmi", "quiet", "talk", "hall", "go", "jimmi", "sai", "control", "franci", "worri", "go", "jimmi", "give", "inform", "there", "anoth", "shoot", "hous", "first", "saw", "tezo", "the", "men", "look", "see", "cop", "blood", "splatter", "cut", "rai", "look", "around", "see", "shot", "execut", "style", "tezo", "girlfriend", "saw", "give", "potato", "rai", "squeez", "talk", "spanish", "eventu", "reveal", "rai", "threaten", "take", "kid", "awai", "tezo", "tip", "gui", "call", "sandi", "polic", "depart", "rai", "sai", "noth", "detect", "scene", "inform", "walk", "there", "larg", "funer", "process", "dead", "offic", "franci", "jr", "larg", "roll", "co", "after", "done", "rai", "catch", "start", "grill", "might", "go", "divis", "hi", "brother", "start", "take", "offens", "get", "heat", "convers", "rai", "sai", "tezo", "girl", "drop", "name", "sandi", "polic", "offic", "tezo", "phone", "call", "peopl", "outsid", "someon", "knew", "bust", "four", "men", "rai", "ask", "anyon", "goe", "nicknam", "depart", "franci", "jr", "look", "shadi", "deni", "anyon", "rai", "franci", "jr", "part", "wai", "unhappi", "franci", "sr", "meet", "rai", "boat", "ask", "happen", "brother", "rai", "explain", "think", "might", "go", "father", "sai", "sit", "see", "realli", "happen", "stir", "mess", "protect", "rai", "obvious", "like", "father", "order", "rai", "reluctantli", "agre", "franci", "jr", "confront", "sandi", "polic", "shower", "kick", "everyon", "els", "sandi", "turn", "start", "cry", "feel", "remors", "he", "tell", "franci", "jr", "jimmi", "drug", "deal", "ton", "plan", "execut", "want", "tezo", "dead", "could", "start", "work", "casado", "rick", "gonzalez", "franci", "shock", "hear", "brother", "law", "sandi", "said", "thought", "franci", "knew", "everyth", "everyon", "knew", "franci", "jr", "tell", "sandi", "give", "badg", "gun", "immedi", "never", "sai", "anyth", "come", "cut", "pension", "sandi", "tell", "franci", "jr", "forc", "franci", "jr", "sai", "sandi", "anymor", "end", "shot", "sandi", "cry", "shower", "floor", "abbi", "sit", "look", "children", "start", "cry", "dy", "go", "leav", "she", "hear", "car", "pull", "franci", "jr", "sit", "car", "upset", "move", "wife", "tri", "stop", "cry", "upstair", "jimmi", "wife", "plai", "kid", "thei", "fun", "thei", "bring", "kid", "show", "foozbal", "tabl", "huge", "tv", "the", "doorbel", "ring", "gangbang", "look", "person", "door", "ask", "jimmi", "jimmi", "come", "order", "gui", "back", "jimmi", "wife", "nervou", "go", "the", "man", "casado", "upset", "jimmi", "keep", "part", "deal", "kill", "tezo", "he", "ask", "jimmi", "slip", "jimmi", "end", "pin", "wall", "sai", "go", "take", "care", "threaten", "casado", "ever", "come", "near", "place", "famili", "jimmi", "call", "crew", "find", "tezo", "right", "hand", "man", "town", "bust", "door", "break", "dinner", "thei", "throw", "man", "floor", "beat", "sai", "tezo", "final", "push", "wife", "take", "infant", "hold", "iron", "board", "jimmi", "tell", "kenni", "call", "child", "servic", "call", "babi", "disfigur", "face", "he", "take", "hot", "iron", "start", "move", "closer", "child", "face", "the", "mother", "scream", "man", "tell", "polic", "want", "know", "eventu", "reveal", "tezo", "jimmi", "leav", "give", "babi", "back", "mother", "unharm", "rai", "track", "on", "old", "ci", "junki", "take", "stash", "destroi", "stooli", "tell", "tezo", "rai", "call", "locat", "tell", "task", "forc", "get", "when", "arriv", "outsid", "build", "start", "scope", "hear", "gunshot", "he", "call", "backup", "start", "go", "stair", "scare", "tenant", "point", "upward", "final", "get", "floor", "see", "dead", "bodi", "hear", "scream", "yell", "rai", "look", "find", "tezo", "bathtub", "jimmi", "stand", "shove", "nightstick", "throat", "rai", "yell", "pull", "nightstick", "man", "throat", "sai", "still", "aliv", "get", "help", "jimmi", "pull", "rai", "gun", "rai", "holster", "shoot", "tezo", "three", "time", "chest", "he", "hand", "gun", "back", "sai", "rai", "sai", "first", "scene", "shot", "bastard", "kill", "four", "cop", "rai", "ask", "insan", "jimmi", "push", "wall", "sai", "cop", "go", "stori", "rai", "franci", "jr", "outsid", "rai", "boathous", "rai", "upset", "tell", "franci", "happen", "ask", "franci", "li", "know", "sandi", "franci", "ask", "rai", "go", "rai", "sai", "much", "want", "get", "blood", "walk", "boathous", "franci", "jr", "pour", "bath", "wife", "abbi", "tell", "upset", "she", "ask", "go", "silent", "she", "beg", "start", "franci", "jr", "sai", "realli", "deep", "know", "scare", "abbi", "look", "shock", "sick", "ask", "wai", "make", "right", "franci", "jr", "sai", "wai", "it", "bring", "everyth", "work", "crumbl", "abbi", "repli", "know", "good", "man", "trust", "trust", "children", "she", "want", "continu", "good", "man", "franci", "jr", "repli", "abbi", "back", "cut", "larg", "offic", "newspap", "room", "there", "sort", "theori", "go", "around", "fact", "tezo", "mouth", "bust", "appar", "splinter", "throat", "circul", "thi", "big", "new", "a", "call", "come", "report", "take", "man", "want", "meet", "thei", "meet", "rain", "cold", "park", "lot", "person", "call", "dishevel", "look", "sandi", "the", "report", "hide", "tape", "record", "seat", "tell", "sandi", "record", "devic", "around", "sandi", "get", "back", "seat", "car", "sandi", "mention", "name", "sai", "everyon", "thei", "sold", "shield", "highest", "bidder", "thei", "kill", "peopl", "dealt", "drug", "took", "payout", "he", "want", "good", "cop", "protect", "serv", "pride", "job", "blue", "uniform", "but", "turn", "bad", "the", "report", "tri", "tell", "sandi", "make", "stori", "get", "truth", "sandi", "put", "white", "cloth", "head", "shoot", "splatter", "blood", "rear", "windshield", "press", "confer", "polic", "pin", "vigilant", "problem", "four", "offic", "alreadi", "dead", "sandi", "franci", "jr", "confront", "franci", "sr", "ask", "son", "much", "knew", "franci", "jr", "repli", "knew", "enough", "hi", "father", "express", "huge", "distast", "start", "chide", "son", "franci", "jr", "break", "father", "must", "time", "push", "came", "shove", "hi", "father", "repli", "never", "took", "payout", "son", "look", "shock", "sai", "never", "ever", "took", "monei", "either", "he", "leav", "sai", "thing", "leav", "father", "look", "distraught", "rai", "pick", "street", "vendor", "food", "wander", "around", "less", "reput", "part", "nyc", "a", "person", "tail", "rai", "walk", "bit", "confront", "tail", "it", "report", "the", "report", "sai", "know", "happen", "impli", "rai", "pretti", "good", "cop", "howev", "knew", "rai", "li", "case", "year", "back", "protect", "cop", "refer", "begin", "rai", "small", "breakdown", "he", "tell", "rai", "want", "truth", "come", "peopl", "older", "brother", "divis", "bring", "rai", "rai", "leav", "angri", "upset", "in", "bar", "franci", "jr", "come", "look", "jimmi", "go", "men", "room", "franci", "jr", "ask", "jimmi", "hell", "go", "jimmi", "sai", "franci", "jr", "told", "the", "collar", "crime", "franci", "jr", "sai", "know", "never", "mind", "jimmi", "pad", "incom", "littl", "total", "hand", "he", "also", "sai", "jimmi", "think", "rai", "go", "turn", "lie", "iab", "intern", "affair", "bureau", "wrong", "rai", "someth", "like", "jimmi", "tri", "give", "franci", "jr", "bunch", "monei", "sai", "part", "take", "franci", "jr", "stare", "monei", "leav", "jimmi", "see", "thing", "crumbl", "look", "distraught", "rai", "get", "woken", "boathous", "call", "sai", "need", "give", "statement", "iab", "rai", "want", "thought", "time", "goe", "there", "ton", "report", "outsid", "well", "protest", "learn", "tezo", "brutal", "teeth", "found", "stomach", "lot", "nasti", "thing", "rai", "iab", "shake", "hand", "men", "obvious", "respect", "lot", "when", "ask", "happen", "rai", "paus", "long", "time", "tell", "go", "go", "want", "he", "sai", "on", "shot", "tezo", "sai", "shot", "he", "respectfulli", "declin", "make", "statement", "it", "wai", "true", "depart", "franci", "sr", "see", "video", "jimmi", "sai", "rai", "kill", "tezo", "ly", "anoth", "high", "person", "depart", "sai", "offic", "will", "testifi", "exactli", "happen", "rai", "set", "franci", "sr", "sai", "son", "ever", "kill", "anyon", "like", "he", "walk", "offic", "watch", "video", "rai", "franci", "sr", "fight", "rai", "it", "vacil", "lot", "franci", "sr", "want", "depart", "take", "fall", "rai", "still", "burnt", "lie", "told", "tell", "father", "save", "depart", "year", "ago", "refus", "he", "franci", "sr", "wife", "even", "come", "driven", "yell", "husband", "franci", "sr", "wai", "order", "rai", "lie", "happen", "follow", "jimmi", "origin", "stori", "franci", "jr", "come", "tell", "father", "stop", "he", "go", "tell", "everyth", "know", "corrupt", "divis", "start", "work", "rai", "clear", "everyth", "first", "go", "find", "jimmi", "jimmi", "bar", "call", "irish", "ey", "franci", "jr", "rai", "head", "kenni", "eddi", "car", "drive", "eddi", "sai", "need", "monei", "kenni", "sai", "need", "lai", "low", "cite", "jimmi", "told", "eddi", "sai", "pai", "rent", "goe", "conveni", "store", "tri", "rob", "he", "get", "shot", "peopl", "start", "look", "around", "gangbang", "start", "notic", "rucku", "kenni", "run", "see", "man", "hold", "someth", "shoot", "cell", "phone", "kenni", "start", "panic", "know", "seriou", "problem", "some", "gang", "member", "upset", "polic", "murder", "hit", "press", "start", "smash", "car", "throw", "thing", "store", "kenni", "lock", "store", "tri", "get", "polic", "back", "exit", "he", "hole", "us", "owner", "hostag", "franci", "jr", "get", "call", "kenni", "rai", "sai", "take", "care", "jimmi", "franci", "jr", "need", "take", "care", "kenni", "/", "hostag", "situat", "kenni", "frantic", "call", "jimmi", "ask", "get", "mess", "it", "impli", "jimmi", "answer", "phone", "franci", "jr", "goe", "door", "talk", "kenni", "get", "open", "door", "sai", "want", "help", "franci", "sr", "get", "call", "offic", "look", "rai", "arrest", "franci", "sr", "sai", "honestli", "rai", "even", "though", "car", "outsid", "the", "detective/offic", "ask", "come", "franci", "sr", "refus", "jimmi", "sit", "bar", "look", "pictur", "wife", "kid", "drink", "depress", "rai", "come", "flash", "badg", "order", "everyon", "rai", "sai", "go", "make", "thing", "right", "hold", "gun", "jimmi", "tell", "put", "gun", "bar", "thei", "put", "gun", "badg", "cuff", "bar", "prepar", "duke", "whoever", "win", "take", "on", "thei", "fight", "knock", "tabl", "chair", "fling", "onto", "bar", "scatter", "jimmi", "photo", "famili", "final", "land", "pool", "tabl", "thing", "look", "rough", "rai", "grab", "cue", "ball", "bean", "jimmi", "twice", "jimmi", "fall", "ground", "daze", "rai", "fall", "hurt", "better", "franci", "jr", "talk", "kenni", "get", "store", "car", "awai", "meanwhil", "whole", "neighbourhood", "arm", "polic", "problem", "on", "ringlead", "get", "everyon", "rile", "tezo", "right", "hand", "man", "almost", "got", "kid", "burnt", "jimmi", "when", "see", "kenni", "get", "taken", "awai", "crowd", "start", "dispers", "still", "pretti", "angri", "rai", "jimmi", "cuff", "take", "standoff", "happen", "block", "awai", "crowd", "start", "come", "toward", "thei", "want", "jimmi", "the", "tezo", "right", "hand", "man", "realli", "want", "thei", "pull", "jimmi", "awai", "rai", "hold", "rai", "beef", "jimmi", "look", "toward", "rai", "tell", "tell", "wife", "love", "thei", "arm", "jimmi", "basebal", "bat", "man", "crowbar", "jimmi", "realiz", "end", "drop", "basebal", "bat", "the", "man", "lam", "head", "crowbar", "rai", "scream", "struggl", "punch", "on", "shut", "beat", "jimmi", "pulp", "rai", "stagger", "hostag", "scene", "wind", "franci", "jr", "talk", "superior", "see", "walk", "awai", "tend", "brother", "music", "plai", "word", "obviou", "rai", "tell", "brother", "happen", "jimmi", "thei", "get", "car", "drive", "rai", "franci", "jr", "franci", "sr", "full", "dress", "uniform", "car", "pull", "courthous", "there", "report", "everywher", "thei", "look", "get", "car", "togeth", "three", "go", "stair", "courthous", "reflect", "revolv", "door", "final", "shot", "shake", "hand", "prosecutors/investigator/bigwig", "presum", "go", "testifi"], "tmdb_score_value": 6.3, "tmdb_score_count": 324, "imdb_score_value": 6.7, "imdb_score_count": 55816, "meta_score_value": 45.0, "meta_score_count": 29}