{"id": "tt1355630", "cast": [{"character": "Mia Hall", "name": "Chlo\u00eb Grace Moretz"}, {"character": "Adam Wilde", "name": "Jamie Blackley"}, {"character": "Kim Schein", "name": "Liana Liberato"}, {"character": "Kat Hall", "name": "Mireille Enos"}, {"character": "Denny Hall", "name": "Joshua Leonard"}, {"character": "Gramps", "name": "Stacy Keach"}, {"character": "Gran", "name": "Gabrielle Rose"}, {"character": "Teddy Hall", "name": "Jakob Davies"}, {"character": "Liz", "name": "Ali Milner"}, {"character": "Nurse Ramirez", "name": "Aisha Hinds"}, {"character": "Young Mia", "name": "Gabrielle Cerys Haslett"}, {"character": "Willow", "name": "Lauren Lee Smith"}, {"character": "Henry", "name": "Adam Solomonian"}, {"character": "Surgeon", "name": "John Emmet Tracy"}, {"character": "Liddy", "name": "Chelah Horsdal"}, {"character": "Nurse Davis", "name": "Christine Willes"}, {"character": "Astrid", "name": "Arielle Tuliao"}, {"character": "Cute Groupie", "name": "Sarah Grey"}, {"character": "Male EMT", "name": "William C. Vaughan"}, {"character": "Surgeon", "name": "Paul Jarrett"}], "crew": [{"job": "Director", "name": "R.J. Cutler"}, {"job": "Screenplay", "name": "Shauna Cross"}, {"job": "Producer", "name": "Alison Greenspan"}, {"job": "Original Music Composer", "name": "Heitor Pereira"}], "title": "If I Stay", "genres": ["Drama"], "keywords": ["coma", "musician", "teenage girl", "car accident", "teenager", "based on young adult novel"], "original_language": "English", "rating": "PG-13", "release_date": "2014-08-21", "revenue": 78874840.0, "runtime": 106, "summary": "Mia Hall thought the hardest decision she would ever face would be whether to pursue her musical dreams at Juilliard or follow a different path to be with the love of her life, Adam. But what should have been a carefree family drive changes everything in an instant, and now her own life hangs in the balance. Caught between life and death for one revealing day, Mia has only one decision left, which will not only decide her future but her ultimate fate.", "tmdb_score_value": 7.3, "tmdb_score_count": 1842, "imdb_score_value": 6.8, "imdb_score_count": 99455, "meta_score_value": 46.0, "meta_score_count": 36}