{"id": "tt1641638", "cast": [{"character": "Ip Man", "name": "Dennis To Yue-Hong"}, {"character": "Cheung Wing Shing", "name": "Crystal Huang Yi"}, {"character": "Ng Chung So", "name": "Yuen Biao"}, {"character": "Ip Tin-chi", "name": "Fan Siu-Wong"}, {"character": "Li Mei Wai", "name": "Rose Chan Ka-Wun"}, {"character": "Leung Bik", "name": "Yip Chun"}, {"character": "Chan Wah-Shun", "name": "Sammo Hung"}, {"character": "Kitano Yumi", "name": "Bernice Liu"}, {"character": "Deputy mayor Cheung Ho-Tin", "name": "Lam Suet"}, {"character": "Young Li Mei Wai", "name": "Xu Jiao"}, {"character": "Chairman Li Man Ho", "name": "Heman Leung"}, {"character": "Young Ip Man", "name": "Jun Hui Wen"}, {"character": "Young Ip Tin Chi", "name": "Shen Al Ji"}, {"character": "Cheung Wing-Wah", "name": "Sire Ma"}, {"character": "Sheriff", "name": "Kwok-Lun Lee"}, {"character": "Kitano Yukio", "name": "Kenya Sawada"}, {"character": "Ip's father", "name": "Chen Zhi-Hui"}, {"character": "Sui San", "name": "Zhang Chi"}, {"character": "Yao Choi", "name": "Xueliang Zhu"}, {"character": "Rogue", "name": "Ding Xiao-Lung"}], "crew": [{"job": "Director", "name": "Herman Yau"}, {"job": "Screenplay", "name": "Erica Lee"}, {"job": "Producer", "name": "Sin Kwok-lam"}, {"job": "Original Music Composer", "name": "Mak Chun-Hung"}], "title": "The Legend Is Born: Ip Man", "genres": ["Drama", "Action", "History"], "keywords": ["martial arts"], "original_language": "Cantonese", "rating": "NOT RATED", "release_date": "2010-06-24", "revenue": 0.0, "runtime": 100, "summary": "Yip Man's resistance against invading foreigners, along with his romantic relations while under the tutelage of three Wing Chun masters.", "tmdb_score_value": 6.6, "tmdb_score_count": 272, "imdb_score_value": 7.1, "imdb_score_count": 28357, "meta_score_value": 0.0, "meta_score_count": 0}