{"id": "tt1686784", "cast": [{"character": "Chow Wai On", "name": "Jet Li"}, {"character": "Jade", "name": "Zhou Xun"}, {"character": "Yu Hua Tian", "name": "Chen Kun"}, {"character": "Tribal Princess", "name": "Kwai Lun-Mei"}, {"character": "Gu Shaotang", "name": "Li Yu-Chun"}, {"character": "Ma Jinliang", "name": "Fan Siu-Wong"}, {"character": "Su Huirong", "name": "Mavis Fan"}, {"character": "Ji Xueyong", "name": "Du Yi-Heng"}, {"character": "Zhao Tong", "name": "Dillon Wu Di"}, {"character": "Imperial consort Wan", "name": "Viann Zhang"}, {"character": "Tan Luzi", "name": "Sheng Jian"}, {"character": "Eunuch Wan Yulou", "name": "Gordon Liu Chia-Hui"}], "crew": [{"job": "Director", "name": "Tsui Hark"}, {"job": "Writer", "name": "Tsui Hark"}, {"job": "Producer", "name": "Tsui Hark"}, {"job": "Producer", "name": "Nansun Shi"}, {"job": "Producer", "name": "Jeffrey Chan"}, {"job": "Original Music Composer", "name": "William Wu Wai-Lap"}], "title": "Flying Swords of Dragon Gate", "genres": ["Adventure", "Action"], "keywords": [], "original_language": "Chinese", "rating": "R", "release_date": "2011-12-15", "revenue": 0.0, "runtime": 125, "summary": "Set three years after Dragon Inn, innkeeper Jade has disappeared and a new inn has risen from the ashes - one that's staffed by marauders masquerading as law-abiding citizens, who hope to unearth the fabled lost city buried in the desert.", "tokens": ["set", "three", "year", "dragon", "inn", "innkeep", "jade", "disappear", "new", "inn", "risen", "ash", "on", "staf", "maraud", "masquerad", "law", "abid", "citizen", "hope", "unearth", "fabl", "lost", "citi", "buri", "desert"], "tmdb_score_value": 5.9, "tmdb_score_count": 64, "imdb_score_value": 6.0, "imdb_score_count": 6988, "meta_score_value": 57.0, "meta_score_count": 10}