{"id": "tt2438644", "cast": [{"character": "Carl M\u00f8rk", "name": "Nikolaj Lie Kaas"}, {"character": "Assad", "name": "Fares Fares"}, {"character": "Merete Lynggaard", "name": "Sonja Richter"}, {"character": "Uffe Lynggaard", "name": "Mikkel Boe F\u00f8lsgaard"}, {"character": "Marcus Jacobsen", "name": "S\u00f8ren Pilmark"}, {"character": "Hardy", "name": "Troels Lyby"}, {"character": "Helle", "name": "Marie Mondrup"}, {"character": "Johan Lundquist", "name": "Eric Ericson"}, {"character": "Tereza", "name": "Marijana Jankovic"}, {"character": "Larsson", "name": "Claes Ljungmark"}, {"character": "Lasses plejemor", "name": "Dorte H\u00f8jsted"}], "crew": [{"job": "Director", "name": "Mikkel N\u00f8rgaard"}, {"job": "Writer", "name": "Nikolaj Arcel"}], "title": "The Keeper of Lost Causes", "genres": ["Thriller", "Mystery", "Crime"], "keywords": ["denmark", "copenhagen", "based on novel", "danish"], "original_language": "Danish", "rating": "NOT RATED", "release_date": "2013-10-03", "revenue": 0.0, "runtime": 100, "summary": "Chief detective Carl M\u00f8rck and his assistant Assad become involved in a five-year-old case concerning the mystery of politician Merete Lynggaard's disappearance - a journey that takes them deep into the undercurrent of abuse and malice that lurks beneath the polished surface of Scandinavia.", "tmdb_score_value": 7.1, "tmdb_score_count": 204, "imdb_score_value": 7.2, "imdb_score_count": 18291, "meta_score_value": 62.0, "meta_score_count": 8}