{"id": "tt3705412", "cast": [{"character": "Brodie", "name": "Milo Cawthorne"}, {"character": "Medina", "name": "Kimberley Crossman"}, {"character": "Dion", "name": "Sam Berkley"}, {"character": "Shanna", "name": "Delaney Tabron"}, {"character": "Uncle Albert", "name": "Colin Moy"}, {"character": "Aunt Mary", "name": "Jodie Rimmer"}, {"character": "Abigail", "name": "Kate Elliott"}, {"character": "Zakk", "name": "James Blake"}, {"character": "Giles", "name": "Daniel Cresswell"}, {"character": "Rikki Daggers", "name": "Stephen Ure"}, {"character": "David", "name": "Nick Hoskins-Smith"}, {"character": "Byron", "name": "Erroll Shand"}, {"character": "Terry", "name": "Aaron McGregor"}, {"character": "Aeon", "name": "Andrew Laing"}, {"character": "Vadin", "name": "Tim Foley"}, {"character": "Mr. Capenhurst", "name": "Cameron Rhodes"}, {"character": "Ron", "name": "Campbell Rousselle"}, {"character": "Brodie's Mum", "name": "Paula Hallagher"}], "crew": [{"job": "Director", "name": "Jason Lei Howden"}, {"job": "Writer", "name": "Jason Lei Howden"}, {"job": "Producer", "name": "Andrew Beattie"}, {"job": "Producer", "name": "Sarah Howden"}, {"job": "Producer", "name": "Morgan Leigh Stewart"}], "title": "Deathgasm", "genres": ["Comedy", "Horror", "Music"], "keywords": ["new zealand", "college", "friendship", "teenage boy", "metal band"], "original_language": "English", "rating": "NOT RATED", "release_date": "2015-08-28", "revenue": 0.0, "runtime": 86, "summary": "Two teenage boys unwittingly summon an ancient evil entity known as The Blind One by delving into black magic while trying to escape their mundane lives.", "tmdb_score_value": 6.3, "tmdb_score_count": 230, "imdb_score_value": 6.3, "imdb_score_count": 12665, "meta_score_value": 65.0, "meta_score_count": 10}